{
  "last_update": "2026-03-31T23:49:43+03:00",
  "source": "multi-parser",
  "total": 114,
  "today_total": 65,
  "matches": [
    {
      "sport": "hockey",
      "league": "Switzerland. 2nd Division",
      "id": "leon_1970324851402036",
      "date": "31 мар",
      "time": "20:45",
      "match_time": "2026-03-31T20:45:00+03:00",
      "team1": "HC La Chaux-de-fonds",
      "team2": "HC Sierre-Anniviers",
      "match_url": "https://leon.ru/events/IceHockey/1970324836976212-Switzerland-2nd-Division/1970324851402036-HC-La-Chaux-de-fonds-HC-Sierre-Anniviers",
      "p1": "1.94",
      "x": "3.80",
      "p2": "1.80",
      "p1x": "1.28",
      "p12": "—",
      "px2": "1.22",
      "source": "Leonbets",
      "total_over": "—",
      "total_under": "—",
      "handicap_1": "—",
      "handicap_2": "—",
      "is_live": true
    },
    {
      "sport": "tennis",
      "league": "ITF Women. USA, Arcadia, Hard",
      "id": "leon_1970324851433974",
      "date": "31 мар",
      "time": "21:24",
      "match_time": "2026-03-31T21:24:00+03:00",
      "team1": "Collins, Kylie",
      "team2": "Ewing, Salma",
      "match_url": "https://leon.ru/events/Tennis/1970324836984149-ITF-Women-USA-Arcadia-Hard/1970324851433974-Collins-Kylie-Ewing-Salma",
      "p1": "1.75",
      "x": "—",
      "p2": "1.89",
      "p1x": "—",
      "p12": "—",
      "px2": "—",
      "source": "Leonbets",
      "total_over": "—",
      "total_under": "—",
      "handicap_1": "—",
      "handicap_2": "—",
      "is_live": true
    },
    {
      "sport": "tennis",
      "league": "ITF Women. USA, Arcadia, Hard",
      "id": "leon_1970324851433971",
      "date": "31 мар",
      "time": "21:26",
      "match_time": "2026-03-31T21:26:00+03:00",
      "team1": "Amelie Van Impe",
      "team2": "Clarke, Chukwumelije",
      "match_url": "https://leon.ru/events/Tennis/1970324836984149-ITF-Women-USA-Arcadia-Hard/1970324851433971-Amelie-Van-Impe-Clarke-Chukwumelije",
      "p1": "1.55",
      "x": "—",
      "p2": "2.17",
      "p1x": "—",
      "p12": "—",
      "px2": "—",
      "source": "Leonbets",
      "total_over": "—",
      "total_under": "—",
      "handicap_1": "—",
      "handicap_2": "—",
      "is_live": true
    },
    {
      "sport": "tennis",
      "league": "ATP. USA, Houston, Clay",
      "id": "leon_1970324851421731",
      "date": "31 мар",
      "time": "21:35",
      "match_time": "2026-03-31T21:35:00+03:00",
      "team1": "Basavareddy, Nishanth",
      "team2": "Liam Draxl",
      "match_url": "https://leon.ru/events/Tennis/1970324837019494-ATP-USA-Houston-Clay/1970324851421731-Basavareddy-Nishanth-Liam-Draxl",
      "p1": "1.50",
      "x": "—",
      "p2": "2.50",
      "p1x": "—",
      "p12": "—",
      "px2": "—",
      "source": "Leonbets",
      "total_over": "—",
      "total_under": "—",
      "handicap_1": "—",
      "handicap_2": "—",
      "is_live": true
    },
    {
      "sport": "tennis",
      "league": "UTR Women. Nashville",
      "id": "leon_1970324851418950",
      "date": "31 мар",
      "time": "21:45",
      "match_time": "2026-03-31T21:45:00+03:00",
      "team1": "Oak, Isabelle",
      "team2": "Peyer, Lena",
      "match_url": "https://leon.ru/events/Tennis/1970324837034118-UTR-Women-Nashville/1970324851418950-Oak-Isabelle-Peyer-Lena",
      "p1": "2.00",
      "x": "—",
      "p2": "1.70",
      "p1x": "—",
      "p12": "—",
      "px2": "—",
      "source": "Leonbets",
      "total_over": "—",
      "total_under": "—",
      "handicap_1": "—",
      "handicap_2": "—",
      "is_live": true
    },
    {
      "sport": "football",
      "league": "World Cup 2026 UEFA Qualification",
      "id": "leon_1970324851390653",
      "date": "31 мар",
      "time": "21:45",
      "match_time": "2026-03-31T21:45:00+03:00",
      "team1": "Bosnia and Herzegovina",
      "team2": "Italy",
      "match_url": "https://leon.ru/events/Soccer/1970324837028794-World-Cup-World-Cup-2026-UEFA-Qualification/1970324851390653-Bosnia-and-Herzegovina-Italy",
      "p1": "1.65",
      "x": "1.32",
      "p2": "2.15",
      "p1x": "—",
      "p12": "—",
      "px2": "—",
      "source": "Leonbets",
      "total_over": "—",
      "total_under": "—",
      "handicap_1": "—",
      "handicap_2": "—",
      "is_live": true
    },
    {
      "sport": "football",
      "league": "World Cup 2026 UEFA Qualification",
      "id": "leon_1970324851390661",
      "date": "31 мар",
      "time": "21:45",
      "match_time": "2026-03-31T21:45:00+03:00",
      "team1": "Czech Republic",
      "team2": "Denmark",
      "match_url": "https://leon.ru/events/Soccer/1970324837028794-World-Cup-World-Cup-2026-UEFA-Qualification/1970324851390661-Czech-Republic-Denmark",
      "p1": "2.35",
      "x": "1.22",
      "p2": "1.55",
      "p1x": "—",
      "p12": "—",
      "px2": "—",
      "source": "Leonbets",
      "total_over": "—",
      "total_under": "—",
      "handicap_1": "—",
      "handicap_2": "—",
      "is_live": true
    },
    {
      "sport": "tennis",
      "league": "ATP Challenger. Brazil, Sao Leopoldo, Clay",
      "id": "leon_1970324851432460",
      "date": "31 мар",
      "time": "21:50",
      "match_time": "2026-03-31T21:50:00+03:00",
      "team1": "Guillen Meza, Alvaro",
      "team2": "Ambrogi, Luciano Emanuel",
      "match_url": "https://leon.ru/events/Tennis/1970324836999819-ATP-Challenger-Brazil-Sao-Leopoldo-Clay/1970324851432460-Guillen-Meza-Alvaro-Ambrogi-Luciano-Emanuel",
      "p1": "1.42",
      "x": "—",
      "p2": "2.60",
      "p1x": "—",
      "p12": "—",
      "px2": "—",
      "source": "Leonbets",
      "total_over": "—",
      "total_under": "—",
      "handicap_1": "—",
      "handicap_2": "—",
      "is_live": true
    },
    {
      "sport": "volleyball",
      "league": "Italy. Regional League U21, Women",
      "id": "leon_1970324851438373",
      "date": "31 мар",
      "time": "21:53",
      "match_time": "2026-03-31T21:53:10.813000+03:00",
      "team1": "Casati Arcore U21",
      "team2": "Sanda Volley W U21",
      "match_url": "https://leon.ru/events/Volleyball/1970324836996624-Italy-Regional-League-U21-Women/1970324851438373-Casati-Arcore-U21-Sanda-Volley-W-U21",
      "p1": "1.03",
      "x": "—",
      "p2": "25.00",
      "p1x": "—",
      "p12": "—",
      "px2": "—",
      "source": "Leonbets",
      "total_over": "—",
      "total_under": "—",
      "handicap_1": "—",
      "handicap_2": "—",
      "is_live": true
    },
    {
      "sport": "tennis",
      "league": "WTA. USA, Charleston, Clay",
      "id": "leon_1970324851421480",
      "date": "31 мар",
      "time": "21:54",
      "match_time": "2026-03-31T21:54:04+03:00",
      "team1": "Polina Kudermetova",
      "team2": "Oliynykova, Oleksandra",
      "match_url": "https://leon.ru/events/Tennis/1970324837034082-WTA-USA-Charleston-Clay/1970324851421480-Polina-Kudermetova-Oliynykova-Oleksandra",
      "p1": "1.90",
      "x": "—",
      "p2": "1.90",
      "p1x": "—",
      "p12": "—",
      "px2": "—",
      "source": "Leonbets",
      "total_over": "—",
      "total_under": "—",
      "handicap_1": "—",
      "handicap_2": "—",
      "is_live": true
    },
    {
      "sport": "tennis",
      "league": "UTR. Nashville",
      "id": "leon_1970324851419663",
      "date": "31 мар",
      "time": "21:55",
      "match_time": "2026-03-31T21:55:00+03:00",
      "team1": "Noroozian, Aram",
      "team2": "John Patrick Popowich",
      "match_url": "https://leon.ru/events/Tennis/1970324837030815-UTR-Nashville/1970324851419663-Noroozian-Aram-John-Patrick-Popowich",
      "p1": "2.05",
      "x": "—",
      "p2": "1.70",
      "p1x": "—",
      "p12": "—",
      "px2": "—",
      "source": "Leonbets",
      "total_over": "—",
      "total_under": "—",
      "handicap_1": "—",
      "handicap_2": "—",
      "is_live": true
    },
    {
      "sport": "tennis",
      "league": "ATP. USA, Houston, Clay",
      "id": "leon_1970324851421728",
      "date": "31 мар",
      "time": "22:00",
      "match_time": "2026-03-31T22:00:00+03:00",
      "team1": "Etcheverry, Tomas Martin",
      "team2": "Gomez, Federico Agustin",
      "match_url": "https://leon.ru/events/Tennis/1970324837019494-ATP-USA-Houston-Clay/1970324851421728-Etcheverry-Tomas-Martin-Gomez-Federico-Agustin",
      "p1": "2.20",
      "x": "—",
      "p2": "1.65",
      "p1x": "—",
      "p12": "—",
      "px2": "—",
      "source": "Leonbets",
      "total_over": "—",
      "total_under": "—",
      "handicap_1": "—",
      "handicap_2": "—",
      "is_live": true
    },
    {
      "sport": "football",
      "league": "Iceland. League Cup Women B",
      "id": "leon_1970324851427775",
      "date": "31 мар",
      "time": "22:00",
      "match_time": "2026-03-31T22:00:00+03:00",
      "team1": "Haukar",
      "team2": "HK Kopavogur W",
      "match_url": "https://leon.ru/events/Soccer/1970324837019175-Iceland-League-Cup-Women-B/1970324851427775-Haukar-HK-Kopavogur-W",
      "p1": "98.00",
      "x": "13.00",
      "p2": "1.04",
      "p1x": "11.48",
      "p12": "1.03",
      "px2": "—",
      "source": "Leonbets",
      "total_over": "—",
      "total_under": "—",
      "handicap_1": "—",
      "handicap_2": "—",
      "is_live": true
    },
    {
      "sport": "football",
      "league": "Spain. Youth Championship",
      "id": "leon_1970324851419642",
      "date": "31 мар",
      "time": "22:00",
      "match_time": "2026-03-31T22:00:00+03:00",
      "team1": "CA Juventud de Las Piedras",
      "team2": "UD Longuera Toscal U19",
      "match_url": "https://leon.ru/events/Soccer/1970324836987753-Spain-Youth-Championship/1970324851419642-CA-Juventud-de-Las-Piedras-UD-Longuera-Toscal-U19",
      "p1": "1.16",
      "x": "1.32",
      "p2": "4.30",
      "p1x": "—",
      "p12": "—",
      "px2": "—",
      "source": "Leonbets",
      "total_over": "—",
      "total_under": "—",
      "handicap_1": "—",
      "handicap_2": "—",
      "is_live": true
    },
    {
      "sport": "baseball",
      "league": "USA. NCAA",
      "id": "leon_1970324851123220",
      "date": "31 мар",
      "time": "22:00",
      "match_time": "2026-03-31T22:00:00+03:00",
      "team1": "Georgia Bulldogs",
      "team2": "Georgia State Panthers",
      "match_url": "https://leon.ru/events/Baseball/1970324836989540-USA-NCAA/1970324851123220-Georgia-Bulldogs-Georgia-State-Panthers",
      "p1": "1.15",
      "x": "2.35",
      "p2": "5.00",
      "p1x": "—",
      "p12": "—",
      "px2": "1.60",
      "source": "Leonbets",
      "total_over": "—",
      "total_under": "—",
      "handicap_1": "—",
      "handicap_2": "—",
      "is_live": true
    },
    {
      "sport": "baseball",
      "league": "USA. NCAA",
      "id": "leon_1970324851384212",
      "date": "31 мар",
      "time": "22:00",
      "match_time": "2026-03-31T22:00:00+03:00",
      "team1": "Saint Johns Red Storm",
      "team2": "Wagner Seahawks",
      "match_url": "https://leon.ru/events/Baseball/1970324836989540-USA-NCAA/1970324851384212-Saint-Johns-Red-Storm-Wagner-Seahawks",
      "p1": "1.60",
      "x": "7.75",
      "p2": "2.35",
      "p1x": "1.33",
      "p12": "—",
      "px2": "1.80",
      "source": "Leonbets",
      "total_over": "—",
      "total_under": "—",
      "handicap_1": "—",
      "handicap_2": "—",
      "is_live": true
    },
    {
      "sport": "football",
      "league": "Uruguay. Primera, Reserves",
      "id": "leon_1970324851432120",
      "date": "31 мар",
      "time": "22:00",
      "match_time": "2026-03-31T22:00:00+03:00",
      "team1": "Colon Reserve",
      "team2": "Deportivo Maldonado Reserve",
      "match_url": "https://leon.ru/events/Soccer/1970324836983511-Uruguay-Primera-Reserves/1970324851432120-Colon-Reserve-Deportivo-Maldonado-Reserve",
      "p1": "1.16",
      "x": "1.45",
      "p2": "4.10",
      "p1x": "—",
      "p12": "—",
      "px2": "1.07",
      "source": "Leonbets",
      "total_over": "—",
      "total_under": "—",
      "handicap_1": "—",
      "handicap_2": "—",
      "is_live": true
    },
    {
      "sport": "football",
      "league": "World. International Friendlies",
      "id": "leon_1970324851399789",
      "date": "31 мар",
      "time": "22:00",
      "match_time": "2026-03-31T22:00:00+03:00",
      "team1": "Burkina Faso",
      "team2": "Guinea Bissau",
      "match_url": "https://leon.ru/events/Soccer/1970324836979757-World-International-Friendlies/1970324851399789-Burkina-Faso-Guinea-Bissau",
      "p1": "1.03",
      "x": "17.50",
      "p2": "701.00",
      "p1x": "—",
      "p12": "1.03",
      "px2": "17.07",
      "source": "Leonbets",
      "total_over": "—",
      "total_under": "—",
      "handicap_1": "—",
      "handicap_2": "—",
      "is_live": true
    },
    {
      "sport": "football",
      "league": "World. International Friendlies",
      "id": "leon_1970324851419534",
      "date": "31 мар",
      "time": "22:00",
      "match_time": "2026-03-31T22:00:00+03:00",
      "team1": "Senegal",
      "team2": "Gambia",
      "match_url": "https://leon.ru/events/Soccer/1970324836979757-World-International-Friendlies/1970324851419534-Senegal-Gambia",
      "p1": "1.10",
      "x": "1.60",
      "p2": "5.00",
      "p1x": "—",
      "p12": "—",
      "px2": "1.21",
      "source": "Leonbets",
      "total_over": "—",
      "total_under": "—",
      "handicap_1": "—",
      "handicap_2": "—",
      "is_live": true
    },
    {
      "sport": "football",
      "league": "World. International Friendlies",
      "id": "leon_1970324851319824",
      "date": "31 мар",
      "time": "22:00",
      "match_time": "2026-03-31T22:00:00+03:00",
      "team1": "Spain",
      "team2": "Egypt",
      "match_url": "https://leon.ru/events/Soccer/1970324836979757-World-International-Friendlies/1970324851319824-Spain-Egypt",
      "p1": "1.05",
      "x": "1.47",
      "p2": "7.50",
      "p1x": "—",
      "p12": "—",
      "px2": "1.23",
      "source": "Leonbets",
      "total_over": "—",
      "total_under": "—",
      "handicap_1": "—",
      "handicap_2": "—",
      "is_live": true
    },
    {
      "sport": "football",
      "league": "World. International Friendlies U20",
      "id": "leon_1970324851425684",
      "date": "31 мар",
      "time": "22:00",
      "match_time": "2026-03-31T22:00:00+03:00",
      "team1": "Brazil U20",
      "team2": "Paraguay U20",
      "match_url": "https://leon.ru/events/Soccer/1970324836979765-World-International-Friendlies-U20/1970324851425684-Brazil-U20-Paraguay-U20",
      "p1": "1.12",
      "x": "8.00",
      "p2": "6.55",
      "p1x": "—",
      "p12": "—",
      "px2": "3.60",
      "source": "Leonbets",
      "total_over": "—",
      "total_under": "—",
      "handicap_1": "—",
      "handicap_2": "—",
      "is_live": true
    },
    {
      "sport": "baseball",
      "league": "USA. Triple A, National Championship",
      "id": "leon_1970324851293081",
      "date": "31 мар",
      "time": "22:05",
      "match_time": "2026-03-31T22:05:00+03:00",
      "team1": "Syracuse Mets",
      "team2": "Toledo Mud Hens",
      "match_url": "https://leon.ru/events/Baseball/1970324836982065-USA-Triple-A-National-Championship/1970324851293081-Syracuse-Mets-Toledo-Mud-Hens",
      "p1": "3.60",
      "x": "1.96",
      "p2": "3.40",
      "p1x": "1.27",
      "p12": "1.75",
      "px2": "1.24",
      "source": "Leonbets",
      "total_over": "—",
      "total_under": "—",
      "handicap_1": "—",
      "handicap_2": "—",
      "is_live": true
    },
    {
      "sport": "tennis",
      "league": "ITF Women. USA, Arcadia, Hard",
      "id": "leon_1970324851433972",
      "date": "31 мар",
      "time": "22:07",
      "match_time": "2026-03-31T22:07:00+03:00",
      "team1": "Grubor, Ana",
      "team2": "Egorova, Daria",
      "match_url": "https://leon.ru/events/Tennis/1970324836984149-ITF-Women-USA-Arcadia-Hard/1970324851433972-Grubor-Ana-Egorova-Daria",
      "p1": "2.12",
      "x": "—",
      "p2": "1.58",
      "p1x": "—",
      "p12": "—",
      "px2": "—",
      "source": "Leonbets",
      "total_over": "—",
      "total_under": "—",
      "handicap_1": "—",
      "handicap_2": "—",
      "is_live": true
    },
    {
      "sport": "basket",
      "league": "Iceland. 1. Delid Karla",
      "id": "leon_1970324851435321",
      "date": "31 мар",
      "time": "22:15",
      "match_time": "2026-03-31T22:15:00+03:00",
      "team1": "FSu Selfoss",
      "team2": "Haukar",
      "match_url": "https://leon.ru/events/Basketball/1970324836988701-Iceland-1-Delid-Karla/1970324851435321-FSu-Selfoss-Haukar",
      "p1": "1.01",
      "x": "—",
      "p2": "25.00",
      "p1x": "—",
      "p12": "—",
      "px2": "—",
      "source": "Leonbets",
      "total_over": "—",
      "total_under": "—",
      "handicap_1": "—",
      "handicap_2": "—",
      "is_live": true
    },
    {
      "sport": "basket",
      "league": "Iceland. 1. Delid Karla",
      "id": "leon_1970324851435322",
      "date": "31 мар",
      "time": "22:15",
      "match_time": "2026-03-31T22:15:00+03:00",
      "team1": "Skallagrímur",
      "team2": "Breidablik",
      "match_url": "https://leon.ru/events/Basketball/1970324836988701-Iceland-1-Delid-Karla/1970324851435322-Skallagrímur-Breidablik",
      "p1": "4.70",
      "x": "—",
      "p2": "1.13",
      "p1x": "—",
      "p12": "—",
      "px2": "—",
      "source": "Leonbets",
      "total_over": "—",
      "total_under": "—",
      "handicap_1": "—",
      "handicap_2": "—",
      "is_live": true
    },
    {
      "sport": "tennis",
      "league": "ATP Challenger. Brazil, Sao Leopoldo, Clay",
      "id": "leon_1970324851432457",
      "date": "31 мар",
      "time": "22:25",
      "match_time": "2026-03-31T22:25:00+03:00",
      "team1": "Zarate, Carlos Maria",
      "team2": "Varillas Patino-Samudio, J",
      "match_url": "https://leon.ru/events/Tennis/1970324836999819-ATP-Challenger-Brazil-Sao-Leopoldo-Clay/1970324851432457-Zarate-Carlos-Maria-Varillas-Patino-Samudio-J",
      "p1": "4.35",
      "x": "—",
      "p2": "1.16",
      "p1x": "—",
      "p12": "—",
      "px2": "—",
      "source": "Leonbets",
      "total_over": "—",
      "total_under": "—",
      "handicap_1": "—",
      "handicap_2": "—",
      "is_live": true
    },
    {
      "sport": "basket",
      "league": "Iceland. Urvalsdeild, Women",
      "id": "leon_1970324851420899",
      "date": "31 мар",
      "time": "22:30",
      "match_time": "2026-03-31T22:30:00+03:00",
      "team1": "KR Reykjavik W",
      "team2": "Keflavik",
      "match_url": "https://leon.ru/events/Basketball/1970324836975953-Iceland-Urvalsdeild-Women/1970324851420899-KR-Reykjavik-W-Keflavik",
      "p1": "1.50",
      "x": "—",
      "p2": "2.31",
      "p1x": "—",
      "p12": "—",
      "px2": "—",
      "source": "Leonbets",
      "total_over": "—",
      "total_under": "—",
      "handicap_1": "—",
      "handicap_2": "—",
      "is_live": true
    },
    {
      "sport": "volleyball",
      "league": "Portugal. Campeonato Nacional",
      "id": "leon_1970324851419481",
      "date": "31 мар",
      "time": "22:30",
      "match_time": "2026-03-31T22:30:00+03:00",
      "team1": "Académica de Espinho",
      "team2": "Vitoria Guimaraes",
      "match_url": "https://leon.ru/events/Volleyball/1970324836994771-Portugal-Campeonato-Nacional/1970324851419481-Académica-de-Espinho-Vitoria-Guimaraes",
      "p1": "1.81",
      "x": "—",
      "p2": "1.83",
      "p1x": "—",
      "p12": "—",
      "px2": "—",
      "source": "Leonbets",
      "total_over": "—",
      "total_under": "—",
      "handicap_1": "—",
      "handicap_2": "—",
      "is_live": true
    },
    {
      "sport": "football",
      "league": "Spain. La Liga 2",
      "id": "leon_1970324847609521",
      "date": "31 мар",
      "time": "22:30",
      "match_time": "2026-03-31T22:30:00+03:00",
      "team1": "Real Valladolid",
      "team2": "Cádiz",
      "match_url": "https://leon.ru/events/Soccer/1970324836975683-Spain-La-Liga-2/1970324847609521-Real-Valladolid-Cádiz",
      "p1": "1.83",
      "x": "17.00",
      "p2": "2.10",
      "p1x": "1.65",
      "p12": "—",
      "px2": "1.87",
      "source": "Leonbets",
      "total_over": "—",
      "total_under": "—",
      "handicap_1": "—",
      "handicap_2": "—",
      "is_live": true
    },
    {
      "sport": "tennis",
      "league": "WTA. Colombia, Bogota, Clay",
      "id": "leon_1970324851411082",
      "date": "31 мар",
      "time": "22:34",
      "match_time": "2026-03-31T22:34:18+03:00",
      "team1": "Emiliana Arango",
      "team2": "Carle, Maria",
      "match_url": "https://leon.ru/events/Tennis/1970324837034080-WTA-Colombia-Bogota-Clay/1970324851411082-Emiliana-Arango-Carle-Maria",
      "p1": "1.78",
      "x": "—",
      "p2": "1.94",
      "p1x": "—",
      "p12": "—",
      "px2": "—",
      "source": "Leonbets",
      "total_over": "—",
      "total_under": "—",
      "handicap_1": "—",
      "handicap_2": "—",
      "is_live": true
    },
    {
      "sport": "tennis",
      "league": "UTR Women. Nashville",
      "id": "leon_1970324851418951",
      "date": "31 мар",
      "time": "22:35",
      "match_time": "2026-03-31T22:35:00+03:00",
      "team1": "Gilbert, Ariana",
      "team2": "Colyer, Rita",
      "match_url": "https://leon.ru/events/Tennis/1970324837034118-UTR-Women-Nashville/1970324851418951-Gilbert-Ariana-Colyer-Rita",
      "p1": "1.35",
      "x": "—",
      "p2": "3.00",
      "p1x": "—",
      "p12": "—",
      "px2": "—",
      "source": "Leonbets",
      "total_over": "—",
      "total_under": "—",
      "handicap_1": "—",
      "handicap_2": "—",
      "is_live": true
    },
    {
      "sport": "tennis",
      "league": "ATP Challenger. Brazil, Sao Leopoldo, Clay",
      "id": "leon_1970324851412171",
      "date": "31 мар",
      "time": "22:50",
      "match_time": "2026-03-31T22:50:00+03:00",
      "team1": "Heide, Gustavo",
      "team2": "Boscardin Dias, Pedro",
      "match_url": "https://leon.ru/events/Tennis/1970324836999819-ATP-Challenger-Brazil-Sao-Leopoldo-Clay/1970324851412171-Heide-Gustavo-Boscardin-Dias-Pedro",
      "p1": "1.52",
      "x": "—",
      "p2": "2.30",
      "p1x": "—",
      "p12": "—",
      "px2": "—",
      "source": "Leonbets",
      "total_over": "—",
      "total_under": "—",
      "handicap_1": "—",
      "handicap_2": "—",
      "is_live": true
    },
    {
      "sport": "tennis",
      "league": "WTA. USA, Charleston, Clay, Doubles",
      "id": "leon_1970324851412325",
      "date": "31 мар",
      "time": "22:55",
      "match_time": "2026-03-31T22:55:53+03:00",
      "team1": "Brady J / Routliffe E",
      "team2": "Muhammad, Asia/Pegula, J",
      "match_url": "https://leon.ru/events/Tennis/1970324837034081-WTA-USA-Charleston-Clay-Doubles/1970324851412325-Brady-J-Routliffe-E-Muhammad-Asia-Pegula-J",
      "p1": "1.60",
      "x": "—",
      "p2": "2.35",
      "p1x": "—",
      "p12": "—",
      "px2": "—",
      "source": "Leonbets",
      "total_over": "—",
      "total_under": "—",
      "handicap_1": "—",
      "handicap_2": "—",
      "is_live": true
    },
    {
      "sport": "tennis",
      "league": "WTA. Colombia, Bogota, Clay",
      "id": "leon_1970324851411087",
      "date": "31 мар",
      "time": "22:57",
      "match_time": "2026-03-31T22:57:26+03:00",
      "team1": "Vandewinkel, Hanne",
      "team2": "Costoulas, Sofia",
      "match_url": "https://leon.ru/events/Tennis/1970324837034080-WTA-Colombia-Bogota-Clay/1970324851411087-Vandewinkel-Hanne-Costoulas-Sofia",
      "p1": "1.22",
      "x": "—",
      "p2": "3.67",
      "p1x": "—",
      "p12": "—",
      "px2": "—",
      "source": "Leonbets",
      "total_over": "—",
      "total_under": "—",
      "handicap_1": "—",
      "handicap_2": "—",
      "is_live": true
    },
    {
      "sport": "football",
      "league": "Colombia. Primera A, Women",
      "id": "leon_1970324851355911",
      "date": "31 мар",
      "time": "23:00",
      "match_time": "2026-03-31T23:00:00+03:00",
      "team1": "Independiente Medellín",
      "team2": "Deportivo Pasto",
      "match_url": "https://leon.ru/events/Soccer/1970324836987471-Colombia-Primera-A-Women/1970324851355911-Independiente-Medellín-Deportivo-Pasto",
      "p1": "1.37",
      "x": "2.55",
      "p2": "3.20",
      "p1x": "—",
      "p12": "—",
      "px2": "1.42",
      "source": "Leonbets",
      "total_over": "—",
      "total_under": "—",
      "handicap_1": "—",
      "handicap_2": "—",
      "is_live": true
    },
    {
      "sport": "football",
      "league": "Colombia. Primera B",
      "id": "leon_1970324851358335",
      "date": "31 мар",
      "time": "23:00",
      "match_time": "2026-03-31T23:00:00+03:00",
      "team1": "Real Santander",
      "team2": "Envigado FC",
      "match_url": "https://leon.ru/events/Soccer/1970324836979651-Colombia-Primera-B/1970324851358335-Real-Santander-Envigado-FC",
      "p1": "13.50",
      "x": "4.15",
      "p2": "1.26",
      "p1x": "3.17",
      "p12": "1.15",
      "px2": "—",
      "source": "Leonbets",
      "total_over": "—",
      "total_under": "—",
      "handicap_1": "—",
      "handicap_2": "—",
      "is_live": true
    },
    {
      "sport": "football",
      "league": "Colombia. Primera B",
      "id": "leon_1970324851358348",
      "date": "31 мар",
      "time": "23:00",
      "match_time": "2026-03-31T23:00:00+03:00",
      "team1": "Tigres FC",
      "team2": "Barranquilla FC",
      "match_url": "https://leon.ru/events/Soccer/1970324836979651-Colombia-Primera-B/1970324851358348-Tigres-FC-Barranquilla-FC",
      "p1": "1.60",
      "x": "2.50",
      "p2": "2.75",
      "p1x": "—",
      "p12": "1.01",
      "px2": "1.31",
      "source": "Leonbets",
      "total_over": "—",
      "total_under": "—",
      "handicap_1": "—",
      "handicap_2": "—",
      "is_live": true
    },
    {
      "sport": "football",
      "league": "Dominican Republic. Premier League",
      "id": "leon_1970324851425739",
      "date": "31 мар",
      "time": "23:00",
      "match_time": "2026-03-31T23:00:00+03:00",
      "team1": "Universidad O&M",
      "team2": "Salcedo",
      "match_url": "https://leon.ru/events/Soccer/1970324836987605-Dominican-Republic-Premier-League/1970324851425739-Universidad-O-M-Salcedo",
      "p1": "15.00",
      "x": "4.45",
      "p2": "1.22",
      "p1x": "3.43",
      "p12": "1.13",
      "px2": "—",
      "source": "Leonbets",
      "total_over": "—",
      "total_under": "—",
      "handicap_1": "—",
      "handicap_2": "—",
      "is_live": true
    },
    {
      "sport": "football",
      "league": "Iceland. Cup, Women",
      "id": "leon_1970324851436633",
      "date": "31 мар",
      "time": "23:00",
      "match_time": "2026-03-31T23:00:00+03:00",
      "team1": "IA Akranes",
      "team2": "KR Reykjavik",
      "match_url": "https://leon.ru/events/Soccer/1970324836985834-Iceland-Cup-Women/1970324851436633-IA-Akranes-KR-Reykjavik",
      "p1": "7.80",
      "x": "4.15",
      "p2": "1.35",
      "p1x": "2.71",
      "p12": "1.15",
      "px2": "1.02",
      "source": "Leonbets",
      "total_over": "—",
      "total_under": "—",
      "handicap_1": "—",
      "handicap_2": "—",
      "is_live": true
    },
    {
      "sport": "baseball",
      "league": "USA. NCAA",
      "id": "leon_1970324851338417",
      "date": "31 мар",
      "time": "23:00",
      "match_time": "2026-03-31T23:00:00+03:00",
      "team1": "Fordham Rams",
      "team2": "Columbia Lions",
      "match_url": "https://leon.ru/events/Baseball/1970324836989540-USA-NCAA/1970324851338417-Fordham-Rams-Columbia-Lions",
      "p1": "2.60",
      "x": "2.10",
      "p2": "1.42",
      "p1x": "1.16",
      "p12": "—",
      "px2": "—",
      "source": "Leonbets",
      "total_over": "—",
      "total_under": "—",
      "handicap_1": "—",
      "handicap_2": "—",
      "is_live": true
    },
    {
      "sport": "baseball",
      "league": "USA. NCAA",
      "id": "leon_1970324851275824",
      "date": "31 мар",
      "time": "23:00",
      "match_time": "2026-03-31T23:00:00+03:00",
      "team1": "Northwestern Wildcats",
      "team2": "Valparaiso Beacons",
      "match_url": "https://leon.ru/events/Baseball/1970324836989540-USA-NCAA/1970324851275824-Northwestern-Wildcats-Valparaiso-Beacons",
      "p1": "2.30",
      "x": "2.20",
      "p2": "1.55",
      "p1x": "1.12",
      "p12": "—",
      "px2": "—",
      "source": "Leonbets",
      "total_over": "—",
      "total_under": "—",
      "handicap_1": "—",
      "handicap_2": "—",
      "is_live": true
    },
    {
      "sport": "tennis",
      "league": "UTR. Nashville",
      "id": "leon_1970324851419681",
      "date": "31 мар",
      "time": "23:00",
      "match_time": "2026-03-31T23:00:00+03:00",
      "team1": "Murray, Freddy",
      "team2": "Lora, Santiago",
      "match_url": "https://leon.ru/events/Tennis/1970324837030815-UTR-Nashville/1970324851419681-Murray-Freddy-Lora-Santiago",
      "p1": "2.30",
      "x": "—",
      "p2": "1.55",
      "p1x": "—",
      "p12": "—",
      "px2": "—",
      "source": "Leonbets",
      "total_over": "—",
      "total_under": "—",
      "handicap_1": "—",
      "handicap_2": "—",
      "is_live": true
    },
    {
      "sport": "tennis",
      "league": "ATP Challenger. Mexico, San Luis Potosi, Clay",
      "id": "leon_1970324851434108",
      "date": "31 мар",
      "time": "23:05",
      "match_time": "2026-03-31T23:05:00+03:00",
      "team1": "Winegar, Theodore",
      "team2": "Alujas, Rodrigo",
      "match_url": "https://leon.ru/events/Tennis/1970324836996329-ATP-Challenger-Mexico-San-Luis-Potosi-Clay/1970324851434108-Winegar-Theodore-Alujas-Rodrigo",
      "p1": "1.57",
      "x": "—",
      "p2": "2.20",
      "p1x": "—",
      "p12": "—",
      "px2": "—",
      "source": "Leonbets",
      "total_over": "—",
      "total_under": "—",
      "handicap_1": "—",
      "handicap_2": "—",
      "is_live": true
    },
    {
      "sport": "tennis",
      "league": "ATP Challenger. Mexico, San Luis Potosi, Clay",
      "id": "leon_1970324851434110",
      "date": "31 мар",
      "time": "23:10",
      "match_time": "2026-03-31T23:10:00+03:00",
      "team1": "Denolly, C",
      "team2": "McKennon, Maxwell",
      "match_url": "https://leon.ru/events/Tennis/1970324836996329-ATP-Challenger-Mexico-San-Luis-Potosi-Clay/1970324851434110-Denolly-C-McKennon-Maxwell",
      "p1": "1.35",
      "x": "—",
      "p2": "2.85",
      "p1x": "—",
      "p12": "—",
      "px2": "—",
      "source": "Leonbets",
      "total_over": "—",
      "total_under": "—",
      "handicap_1": "—",
      "handicap_2": "—",
      "is_live": true
    },
    {
      "sport": "basket",
      "league": "Russia. IPBL, Pro Division",
      "id": "leon_1970324851442186",
      "date": "31 мар",
      "time": "23:10",
      "match_time": "2026-03-31T23:10:01+03:00",
      "team1": "Chita",
      "team2": "Chelyabinsk",
      "match_url": "https://leon.ru/events/Basketball/1970324837033898-Russia-IPBL-Pro-Division/1970324851442186-Chita-Chelyabinsk",
      "p1": "1.13",
      "x": "—",
      "p2": "7.00",
      "p1x": "—",
      "p12": "—",
      "px2": "—",
      "source": "Leonbets",
      "total_over": "—",
      "total_under": "—",
      "handicap_1": "—",
      "handicap_2": "—",
      "is_live": true
    },
    {
      "sport": "tennis",
      "league": "ITF Women. USA, Arcadia, Hard",
      "id": "leon_1970324851433973",
      "date": "31 мар",
      "time": "23:15",
      "match_time": "2026-03-31T23:15:00+03:00",
      "team1": "Evans, Kailey",
      "team2": "Teixido Garcia, Ares",
      "match_url": "https://leon.ru/events/Tennis/1970324836984149-ITF-Women-USA-Arcadia-Hard/1970324851433973-Evans-Kailey-Teixido-Garcia-Ares",
      "p1": "2.11",
      "x": "—",
      "p2": "1.59",
      "p1x": "—",
      "p12": "—",
      "px2": "—",
      "source": "Leonbets",
      "total_over": "—",
      "total_under": "—",
      "handicap_1": "—",
      "handicap_2": "—",
      "is_live": true
    },
    {
      "sport": "basket",
      "league": "NBA2K. eSports Battle. European Conference (4x5 min./OT-3 min.)",
      "id": "leon_1970324851426077",
      "date": "31 мар",
      "time": "23:30",
      "match_time": "2026-03-31T23:30:00+03:00",
      "team1": "Crvena Zvezda (youngboy)",
      "team2": "Dubai (Koko)",
      "match_url": "https://leon.ru/events/Basketball/1970324837030535-NBA2K-eSports-Battle-European-Conference-4x5-min-OT-3-min-/1970324851426077-Crvena-Zvezda-youngboy-Dubai-Koko-",
      "p1": "1.42",
      "x": "—",
      "p2": "3.38",
      "p1x": "—",
      "p12": "—",
      "px2": "—",
      "source": "Leonbets",
      "total_over": "—",
      "total_under": "—",
      "handicap_1": "—",
      "handicap_2": "—",
      "is_live": true
    },
    {
      "sport": "basket",
      "league": "NBA2K. eSports Battle. European Conference (4x5 min./OT-3 min.)",
      "id": "leon_1970324851426099",
      "date": "31 мар",
      "time": "23:30",
      "match_time": "2026-03-31T23:30:00+03:00",
      "team1": "Fenerbahce (iksvel)",
      "team2": "Hapoel Tel Aviv (Erik)",
      "match_url": "https://leon.ru/events/Basketball/1970324837030535-NBA2K-eSports-Battle-European-Conference-4x5-min-OT-3-min-/1970324851426099-Fenerbahce-iksvel-Hapoel-Tel-Aviv-Erik-",
      "p1": "2.03",
      "x": "—",
      "p2": "2.00",
      "p1x": "—",
      "p12": "—",
      "px2": "—",
      "source": "Leonbets",
      "total_over": "—",
      "total_under": "—",
      "handicap_1": "—",
      "handicap_2": "—",
      "is_live": true
    },
    {
      "sport": "tennis",
      "league": "UTR Women. Newport Beach",
      "id": "leon_1970324851400609",
      "date": "31 мар",
      "time": "23:30",
      "match_time": "2026-03-31T23:30:00+03:00",
      "team1": "Foshee, Isabella",
      "team2": "Mar, Tricia",
      "match_url": "https://leon.ru/events/Tennis/1970324837027449-UTR-Women-Newport-Beach/1970324851400609-Foshee-Isabella-Mar-Tricia",
      "p1": "1.22",
      "x": "—",
      "p2": "3.80",
      "p1x": "—",
      "p12": "—",
      "px2": "—",
      "source": "Leonbets",
      "total_over": "—",
      "total_under": "—",
      "handicap_1": "—",
      "handicap_2": "—",
      "is_live": true
    },
    {
      "sport": "hockey",
      "league": "Electronic Leagues. Ehockey NHL 26 United Esports League (3x4 min.)",
      "id": "leon_1970324851442387",
      "date": "31 мар",
      "time": "23:35",
      "match_time": "2026-03-31T23:35:00+03:00",
      "team1": "Philadelphia Flyers (Bukvice)",
      "team2": "Seattle Kraken (Pat95)",
      "match_url": "https://leon.ru/events/IceHockey/1970324837030861-Electronic-Leagues-Ehockey-NHL-26-United-Esports-League-3x4-min-/1970324851442387-Philadelphia-Flyers-Bukvice-Seattle-Kraken-Pat95-",
      "p1": "4.25",
      "x": "7.00",
      "p2": "1.50",
      "p1x": "2.64",
      "p12": "1.11",
      "px2": "1.24",
      "source": "Leonbets",
      "total_over": "—",
      "total_under": "—",
      "handicap_1": "—",
      "handicap_2": "—",
      "is_live": true
    },
    {
      "sport": "tennis",
      "league": "ATP Challenger. Mexico, San Luis Potosi, Clay",
      "id": "leon_1970324851434107",
      "date": "31 мар",
      "time": "23:40",
      "match_time": "2026-03-31T23:40:00+03:00",
      "team1": "Moreno De Alboran, N",
      "team2": "Tobon, Miguel",
      "match_url": "https://leon.ru/events/Tennis/1970324836996329-ATP-Challenger-Mexico-San-Luis-Potosi-Clay/1970324851434107-Moreno-De-Alboran-N-Tobon-Miguel",
      "p1": "1.70",
      "x": "—",
      "p2": "2.00",
      "p1x": "—",
      "p12": "—",
      "px2": "—",
      "source": "Leonbets",
      "total_over": "—",
      "total_under": "—",
      "handicap_1": "—",
      "handicap_2": "—",
      "is_live": true
    },
    {
      "sport": "tennis",
      "league": "UTR. Nashville",
      "id": "leon_1970324851419660",
      "date": "31 мар",
      "time": "23:40",
      "match_time": "2026-03-31T23:40:00+03:00",
      "team1": "Dziopak, Jonasz",
      "team2": "Bennour Dit Sahli, Anas",
      "match_url": "https://leon.ru/events/Tennis/1970324837030815-UTR-Nashville/1970324851419660-Dziopak-Jonasz-Bennour-Dit-Sahli-Anas",
      "p1": "1.40",
      "x": "—",
      "p2": "2.70",
      "p1x": "—",
      "p12": "—",
      "px2": "—",
      "source": "Leonbets",
      "total_over": "—",
      "total_under": "—",
      "handicap_1": "—",
      "handicap_2": "—",
      "is_live": true
    },
    {
      "sport": "football",
      "league": "FIFA eSports. eSports Battle (2x4 min.)",
      "id": "leon_1970324851433727",
      "date": "31 мар",
      "time": "23:46",
      "match_time": "2026-03-31T23:46:00+03:00",
      "team1": "Fc Porto (giannikid)",
      "team2": "Sporting Cp (Hotshot)",
      "match_url": "https://leon.ru/events/Soccer/1970324836985357-FIFA-eSports-eSports-Battle-2x4-min-/1970324851433727-Fc-Porto-giannikid-Sporting-Cp-Hotshot-",
      "p1": "1.90",
      "x": "2.90",
      "p2": "2.01",
      "p1x": "1.15",
      "p12": "—",
      "px2": "1.19",
      "source": "Leonbets",
      "total_over": "—",
      "total_under": "—",
      "handicap_1": "—",
      "handicap_2": "—",
      "is_live": true
    },
    {
      "sport": "football",
      "league": "FIFA eSports. eSports Battle (2x4 min.)",
      "id": "leon_1970324851433770",
      "date": "31 мар",
      "time": "23:46",
      "match_time": "2026-03-31T23:46:00+03:00",
      "team1": "Sc Braga (kray)",
      "team2": "Vitoria SC (Kodak)",
      "match_url": "https://leon.ru/events/Soccer/1970324836985357-FIFA-eSports-eSports-Battle-2x4-min-/1970324851433770-Sc-Braga-kray-Vitoria-SC-Kodak-",
      "p1": "1.76",
      "x": "4.26",
      "p2": "2.00",
      "p1x": "1.25",
      "p12": "—",
      "px2": "1.36",
      "source": "Leonbets",
      "total_over": "—",
      "total_under": "—",
      "handicap_1": "—",
      "handicap_2": "—",
      "is_live": true
    },
    {
      "sport": "football",
      "league": "World Cup 2026 Inter-confederation Play-offs",
      "id": "leon_1970324851394051",
      "date": "1 апр",
      "time": "00:00",
      "match_time": "2026-04-01T00:00:00+03:00",
      "team1": "Congo DR",
      "team2": "Jamaica",
      "match_url": "https://leon.ru/events/Soccer/1970324837033285-World-Cup-World-Cup-2026-Inter-confederation-Play-offs/1970324851394051-Congo-DR-Jamaica",
      "p1": "2.28",
      "x": "23.80",
      "p2": "1.67",
      "p1x": "2.08",
      "p12": "—",
      "px2": "1.56",
      "source": "Leonbets",
      "total_over": "—",
      "total_under": "—",
      "handicap_1": "—",
      "handicap_2": "—",
      "is_live": false
    },
    {
      "sport": "football",
      "league": "World. International Friendlies",
      "id": "leon_1970324851381698",
      "date": "1 апр",
      "time": "02:00",
      "match_time": "2026-04-01T02:00:00+03:00",
      "team1": "USA",
      "team2": "Portugal",
      "match_url": "https://leon.ru/events/Soccer/1970324836979757-World-International-Friendlies/1970324851381698-USA-Portugal",
      "p1": "2.32",
      "x": "2.53",
      "p2": "1.50",
      "p1x": "1.21",
      "p12": "—",
      "px2": "—",
      "source": "Leonbets",
      "total_over": "—",
      "total_under": "—",
      "handicap_1": "—",
      "handicap_2": "—",
      "is_live": false
    },
    {
      "sport": "football",
      "league": "World. International Friendlies",
      "id": "leon_1970324851411883",
      "date": "1 апр",
      "time": "02:15",
      "match_time": "2026-04-01T02:15:00+03:00",
      "team1": "Argentina",
      "team2": "Zambia",
      "match_url": "https://leon.ru/events/Soccer/1970324836979757-World-International-Friendlies/1970324851411883-Argentina-Zambia",
      "p1": "1.10",
      "x": "3.37",
      "p2": "5.30",
      "p1x": "—",
      "p12": "—",
      "px2": "2.06",
      "source": "Leonbets",
      "total_over": "—",
      "total_under": "—",
      "handicap_1": "—",
      "handicap_2": "—",
      "is_live": false
    },
    {
      "sport": "football",
      "league": "World. International Friendlies",
      "id": "leon_1970324851421766",
      "date": "1 апр",
      "time": "02:30",
      "match_time": "2026-04-01T02:30:00+03:00",
      "team1": "Canada",
      "team2": "Tunisia",
      "match_url": "https://leon.ru/events/Soccer/1970324836979757-World-International-Friendlies/1970324851421766-Canada-Tunisia",
      "p1": "2.59",
      "x": "3.04",
      "p2": "2.59",
      "p1x": "1.40",
      "p12": "1.29",
      "px2": "1.40",
      "source": "Leonbets",
      "total_over": "—",
      "total_under": "—",
      "handicap_1": "—",
      "handicap_2": "—",
      "is_live": false
    },
    {
      "sport": "football",
      "league": "World. International Friendlies",
      "id": "leon_1970324850779263",
      "date": "1 апр",
      "time": "03:00",
      "match_time": "2026-04-01T03:00:00+03:00",
      "team1": "Brazil",
      "team2": "Croatia",
      "match_url": "https://leon.ru/events/Soccer/1970324836979757-World-International-Friendlies/1970324850779263-Brazil-Croatia",
      "p1": "1.58",
      "x": "2.56",
      "p2": "2.15",
      "p1x": "—",
      "p12": "—",
      "px2": "1.17",
      "source": "Leonbets",
      "total_over": "—",
      "total_under": "—",
      "handicap_1": "—",
      "handicap_2": "—",
      "is_live": false
    },
    {
      "sport": "football",
      "league": "World. International Friendlies",
      "id": "leon_1970324851381699",
      "date": "1 апр",
      "time": "04:00",
      "match_time": "2026-04-01T04:00:00+03:00",
      "team1": "Mexico",
      "team2": "Belgium",
      "match_url": "https://leon.ru/events/Soccer/1970324836979757-World-International-Friendlies/1970324851381699-Mexico-Belgium",
      "p1": "1.96",
      "x": "2.60",
      "p2": "1.69",
      "p1x": "1.12",
      "p12": "—",
      "px2": "1.02",
      "source": "Leonbets",
      "total_over": "—",
      "total_under": "—",
      "handicap_1": "—",
      "handicap_2": "—",
      "is_live": false
    },
    {
      "sport": "football",
      "league": "World Cup 2026 Inter-confederation Play-offs",
      "id": "leon_1970324851394034",
      "date": "1 апр",
      "time": "06:00",
      "match_time": "2026-04-01T06:00:00+03:00",
      "team1": "Iraq",
      "team2": "Bolivia",
      "match_url": "https://leon.ru/events/Soccer/1970324837033285-World-Cup-World-Cup-2026-Inter-confederation-Play-offs/1970324851394034-Iraq-Bolivia",
      "p1": "1.82",
      "x": "3.56",
      "p2": "1.82",
      "p1x": "1.20",
      "p12": "—",
      "px2": "1.20",
      "source": "Leonbets",
      "total_over": "—",
      "total_under": "—",
      "handicap_1": "—",
      "handicap_2": "—",
      "is_live": false
    },
    {
      "sport": "football",
      "league": "Spain. La Liga 2",
      "id": "leon_1970324847609513",
      "date": "1 апр",
      "time": "20:00",
      "match_time": "2026-04-01T20:00:00+03:00",
      "team1": "Andorra CF",
      "team2": "Málaga",
      "match_url": "https://leon.ru/events/Soccer/1970324836975683-Spain-La-Liga-2/1970324847609513-Andorra-CF-Málaga",
      "p1": "2.78",
      "x": "2.49",
      "p2": "3.15",
      "p1x": "1.31",
      "p12": "1.48",
      "px2": "1.39",
      "source": "Leonbets",
      "total_over": "—",
      "total_under": "—",
      "handicap_1": "—",
      "handicap_2": "—",
      "is_live": false
    },
    {
      "sport": "football",
      "league": "Spain. La Liga 2",
      "id": "leon_1970324851380575",
      "date": "1 апр",
      "time": "21:00",
      "match_time": "2026-04-01T21:00:00+03:00",
      "team1": "Burgos CF",
      "team2": "Ceuta",
      "match_url": "https://leon.ru/events/Soccer/1970324836975683-Spain-La-Liga-2/1970324851380575-Burgos-CF-Ceuta",
      "p1": "2.24",
      "x": "2.29",
      "p2": "5.10",
      "p1x": "1.13",
      "p12": "1.56",
      "px2": "1.58",
      "source": "Leonbets",
      "total_over": "—",
      "total_under": "—",
      "handicap_1": "—",
      "handicap_2": "—",
      "is_live": false
    },
    {
      "sport": "football",
      "league": "Spain. La Liga 2",
      "id": "leon_1970324847609519",
      "date": "1 апр",
      "time": "21:00",
      "match_time": "2026-04-01T21:00:00+03:00",
      "team1": "Huesca",
      "team2": "Cultural Leonesa",
      "match_url": "https://leon.ru/events/Soccer/1970324836975683-Spain-La-Liga-2/1970324847609519-Huesca-Cultural-Leonesa",
      "p1": "2.45",
      "x": "2.31",
      "p2": "4.21",
      "p1x": "1.19",
      "p12": "1.55",
      "px2": "1.49",
      "source": "Leonbets",
      "total_over": "—",
      "total_under": "—",
      "handicap_1": "—",
      "handicap_2": "—",
      "is_live": false
    },
    {
      "sport": "football",
      "league": "Spain. La Liga 2",
      "id": "leon_1970324847609514",
      "date": "1 апр",
      "time": "22:30",
      "match_time": "2026-04-01T22:30:00+03:00",
      "team1": "Racing Santander",
      "team2": "Real Sporting de Gijon",
      "match_url": "https://leon.ru/events/Soccer/1970324836975683-Spain-La-Liga-2/1970324847609514-Racing-Santander-Real-Sporting-de-Gijon",
      "p1": "2.32",
      "x": "2.62",
      "p2": "3.74",
      "p1x": "1.23",
      "p12": "1.43",
      "px2": "1.54",
      "source": "Leonbets",
      "total_over": "—",
      "total_under": "—",
      "handicap_1": "—",
      "handicap_2": "—",
      "is_live": false
    }
  ]
}